shipyard_azure_data_factory/__init__.py
shipyard_azure_data_factory/azure_data_factory.py
shipyard_azure_data_factory/cli/authtest.py
shipyard_azure_data_factory/cli/trigger_sync.py
shipyard_azure_data_factory-0.1.0.dist-info/METADATA
shipyard_azure_data_factory-0.1.0.dist-info/WHEEL
shipyard_azure_data_factory-0.1.0.dist-info/RECORD
