Metadata-Version: 2.1
Name: shipyard-azure-data-factory
Version: 0.1.0
Summary: This Python wrapper class, AzureDataFactoryClient, is designed to facilitate interaction with Azure Data Factory using the Azure SDK
Author: johnathan-rodriguez
Author-email: johnathan.rodriguez@shipyardapp.com
Requires-Python: >=3.9,<4.0
Classifier: Programming Language :: Python :: 3
Classifier: Programming Language :: Python :: 3.9
Classifier: Programming Language :: Python :: 3.10
Classifier: Programming Language :: Python :: 3.11
Requires-Dist: azure-identity (>=1.17.1,<2.0.0)
Requires-Dist: azure-mgmt-datafactory (>=8.0.0,<9.0.0)
Requires-Dist: azure-mgmt-resource (>=23.1.1,<24.0.0)
Requires-Dist: shipyard-templates (>=0.9.0,<0.10.0)
